{"cameraMode":{"drawMode":0,"name":"Shaded","section":"Shading Mode"},"sceneLighting":true,"audioPlay":false,"sceneViewState":{"m_AlwaysRefresh":false,"showFog":true,"showSkybox":true,"showFlares":true,"showImageEffects":true,"showParticleSystems":true,"showVisualEffectGraphs":true,"m_FxEnabled":true},"in2DMode":false,"pivot":{"x":-37.72530746459961,"y":2.1771485805511476,"z":-2.6761035919189455},"rotation":{"x":0.46063458919525149,"y":-0.023089390248060228,"z":0.011542548425495625,"w":0.8873543739318848},"size":15.897716522216797,"orthographic":false}